[
  {
    "line": 1,
    "elements": [
      {
        "start_timestamp": "2022-02-12T22:20:12.287Z",
        "line": 3,
        "name": "Check login is successful with valid credentials",
        "description": "",
        "id": "feature-to-test-login-fuctionality;check-login-is-successful-with-valid-credentials",
        "type": "scenario",
        "keyword": "Scenario",
        "steps": [
          {
            "result": {
              "duration": 3001800,
              "status": "passed"
            },
            "line": 4,
            "name": "user is on login page",
            "match": {
              "location": "StepDefinitions.LoginSteps.user_is_on_login_page()"
            },
            "keyword": "Given "
          },
          {
            "result": {
              "duration": 999900,
              "status": "passed"
            },
            "line": 5,
            "name": "user enters username and password",
            "match": {
              "location": "StepDefinitions.LoginSteps.user_enters_username_and_password()"
            },
            "keyword": "When "
          },
          {
            "result": {
              "duration": 1002800,
              "status": "passed"
            },
            "line": 6,
            "name": "clicks login button",
            "match": {
              "location": "StepDefinitions.LoginSteps.clicks_login_button()"
            },
            "keyword": "And "
          },
          {
            "result": {
              "duration": 1000400,
              "status": "passed"
            },
            "line": 7,
            "name": "user is navigated to the home page",
            "match": {
              "location": "StepDefinitions.LoginSteps.user_is_navigated_to_the_home_page()"
            },
            "keyword": "Then "
          }
        ]
      }
    ],
    "name": "feature to test login fuctionality",
    "description": "",
    "id": "feature-to-test-login-fuctionality",
    "keyword": "Feature",
    "uri": "file:src/test/resources/Features/login.feature",
    "tags": []
  }
]